py_lead_generation/__init__.py
py_lead_generation/src/__init__.py
py_lead_generation/src/engines/__init__.py
py_lead_generation/src/engines/abstract.py
py_lead_generation/src/engines/base.py
py_lead_generation/src/engines/playwright_config.py
py_lead_generation/src/google_maps/__init__.py
py_lead_generation/src/google_maps/engine.py
py_lead_generation/src/google_search/__init__.py
py_lead_generation/src/misc/__init__.py
py_lead_generation/src/misc/utils.py
py_lead_generation/src/misc/writer.py
py_lead_generation/src/yelp/__init__.py
py_lead_generation/src/yelp/engine.py
py_lead_generation-1.0.1.dist-info/LICENSE
py_lead_generation-1.0.1.dist-info/METADATA
py_lead_generation-1.0.1.dist-info/WHEEL
py_lead_generation-1.0.1.dist-info/top_level.txt
py_lead_generation-1.0.1.dist-info/RECORD
