Metadata-Version: 2.1
Name: py_lead_generation
Version: 1.0.1
Summary: Lead generation scripts
Home-page: https://github.com/Madi-S/Lead-Generation
Author: Madi-S (Madi Shaiken)
Author-email: <khovansky99@gmail.com>
License: MIT
Keywords: python,lead generation,web automation,playwright,google maps,yelp
Classifier: Development Status :: 1 - Planning
Classifier: Intended Audience :: Developers
Classifier: Programming Language :: Python :: 3.10
Classifier: Operating System :: Unix
Classifier: Operating System :: MacOS :: MacOS X
Classifier: Operating System :: Microsoft :: Windows
Requires-Python: >=3.10
License-File: LICENSE
Requires-Dist: playwright
Requires-Dist: beautifulsoup4
Requires-Dist: geopy
